[
  {
    "url": "https://superhuman.com/",
    "status_code": 200,
    "headers": {
      "date": "Fri, 27 Feb 2026 20:13:42 GMT",
      "content-type": "text/html; charset=utf-8",
      "transfer-encoding": "chunked",
      "connection": "keep-alive",
      "content-encoding": "gzip",
      "cf-ray": "9d4a582378e6e231-MRS",
      "cf-cache-status": "DYNAMIC",
      "access-control-allow-origin": "*",
      "set-cookie": "gr-wc-st=; Path=/; Max-Age=0; Expires=Thu, 01 Jan 1970 00:00:00 GMT; Secure; HttpOnly; SameSite=Strict, gr-wc-cs=; Path=/; Max-Age=0; Expires=Thu, 01 Jan 1970 00:00:00 GMT; Secure; HttpOnly; SameSite=Strict, gr-wc-tkn=; Path=/; Max-Age=0; Expires=Thu, 01 Jan 1970 00:00:00 GMT; Secure; HttpOnly; SameSite=Strict, gnar_containerId=Q9OkBb7mqT0X; Max-Age=315360000; Domain=.superhuman.com; Path=/; Secure; SameSite=None, gnar_websiteSessionId=8031daec-5717-41cc-a86e-a789096ae5eb; Max-Age=1800; Domain=.superhuman.com; Path=/; Secure; SameSite=None",
      "strict-transport-security": "max-age=15552000",
      "via": "1.1 c06f5d2130689f511352f5187fabf420.cloudfront.net (CloudFront)",
      "content-security-policy": "frame-ancestors 'none'",
      "x-sh-cloudflare": "MPXBAxZaY2VPBf@hvB*b",
      "access-control-allow-credentials": "true",
      "cross-origin-opener-policy": "same-origin",
      "cross-origin-resource-policy": "same-origin",
      "origin-agent-cluster": "?1",
      "referrer-policy": "no-referrer, strict-origin-when-cross-origin",
      "x-amz-cf-id": "zlMLrqOajXBDVTtuSgbthnNqNR4uILTqqJUFIisfUkCwzQKKBKy8JA==",
      "x-amz-cf-pop": "MRS52-P1",
      "x-cache": "Miss from cloudfront",
      "x-content-type-options": "nosniff",
      "x-dns-prefetch-control": "off",
      "x-download-options": "noopen",
      "x-frame-options": "SAMEORIGIN, SAMEORIGIN",
      "x-permitted-cross-domain-policies": "none",
      "x-request-id": "req-1osc",
      "x-xss-protection": "0",
      "vary": "Accept-Encoding",
      "server": "cloudflare"
    },
    "timestamp": "2026-02-27T23:14:07.627442"
  }
]